todomeki/__init__.py
todomeki-0.1.2.dist-info/METADATA
todomeki-0.1.2.dist-info/WHEEL
todomeki-0.1.2.dist-info/top_level.txt
todomeki-0.1.2.dist-info/RECORD
