Metadata-Version: 2.1
Name: todomeki
Version: 0.1.2
Summary: Track event details from web resultse
Home-page: https://github.com/BiscuitBobby/todomeki
Author: BiscuitBobby
Requires-Dist: typing-extensions
Requires-Dist: selenium-screenshot
Requires-Dist: google-generativeai
Requires-Dist: setuptools (~=66.1.1)
Requires-Dist: selenium (~=4.15.2)
Requires-Dist: langchain (~=0.0.354)
Requires-Dist: requests (~=2.31.0)
